gr8gen/__init__.py
gr8gen/__main__.py
gr8gen/utils.py
gr8gen/templates/service.proto.jinja
gr8gen-0.1.2.dist-info/METADATA
gr8gen-0.1.2.dist-info/WHEEL
gr8gen-0.1.2.dist-info/entry_points.txt
gr8gen-0.1.2.dist-info/RECORD
