Metadata-Version: 2.4
Name: gr8gen
Version: 0.1.2
Summary: gr8gen: protobuf generator for gr8pc
Project-URL: Homepage, https://github.com/lucas-labs/gr8pc
Project-URL: Documentation, https://github.com/lucas-labs/gr8pc
Project-URL: Repository, https://github.com/lucas-labs/gr8pc
Author-email: Lucas Colombo <lucasncolombo@gmail.com>
License-Expression: MIT
Requires-Python: >=3.11
Requires-Dist: jinja2>=3.1.4
